H16Trader/__init__.py
H16Trader/core.py
test/__init__.py
test/test_core.py
h16trader-0.1.0.dist-info/LICENSE
h16trader-0.1.0.dist-info/METADATA
h16trader-0.1.0.dist-info/WHEEL
h16trader-0.1.0.dist-info/top_level.txt
h16trader-0.1.0.dist-info/RECORD
